[
  {
    "element_id": 408326,
    "colour": "Black",
    "category": "Buildings & Furniture",
    "design": 4083,
    "element_name": "HANGER 1X4X2",
    "element_in_sets": 129,
    "element_introduced_in": 1995,
    "design_in_sets": 312,
    "design_introduced_in": 1994
  },
  {
    "element_id": 615726,
    "colour": "Black",
    "category": "Vehicles & Transportation",
    "design": 6157,
    "element_name": "BEARING ELEMENT 2X2 2/3",
    "element_in_sets": 265,
    "element_introduced_in": 1994,
    "design_in_sets": 415,
    "design_introduced_in": 1994
  },
  {
    "element_id": 4144024,
    "colour": "Black",
    "category": "Plates",
    "design": 32530,
    "element_name": "T-BEAM W. PLATE 1X2 W. TUBE",
    "element_in_sets": 185,
    "element_introduced_in": 1991,
    "design_in_sets": 543,
    "design_introduced_in": 1991
  },
  {
    "element_id": 4223247,
    "colour": "Black",
    "category": "Minifigure Accessories",
    "design": 30377,
    "element_name": "SPACE SKELETON ARM",
    "element_in_sets": 145,
    "element_introduced_in": 2004,
    "design_in_sets": 377,
    "design_introduced_in": 2003
  },
  {
    "element_id": 4282746,
    "colour": "Black",
    "category": "Plates",
    "design": 2436,
    "element_name": "ANGLE PLATE 1X2/1X4",
    "element_in_sets": 109,
    "element_introduced_in": 2003,
    "design_in_sets": 486,
    "design_introduced_in": 1992
  },
  {
    "element_id": 4508215,
    "colour": "Black",
    "category": "Vehicles & Transportation",
    "design": 30028,
    "element_name": "TYRE NORMAL WIDE Ø14.6 X 9",
    "element_in_sets": 200,
    "element_introduced_in": 1997,
    "design_in_sets": 200,
    "design_introduced_in": 1997
  },
  {
    "element_id": 4516843,
    "colour": "Black",
    "category": "Vehicles & Transportation",
    "design": 59895,
    "element_name": "TYRE D8, SEBS",
    "element_in_sets": 256,
    "element_introduced_in": 2006,
    "design_in_sets": 256,
    "design_introduced_in": 2006
  },
  {
    "element_id": 4121715,
    "colour": "Black",
    "category": "Connectors",
    "design": 2780,
    "element_name": "CONNECTOR PEG W. FRICTION",
    "element_in_sets": 2207,
    "element_introduced_in": 1993,
    "design_in_sets": 2207,
    "design_introduced_in": 1993
  },
  {
    "element_id": 302323,
    "colour": "Bright Blue",
    "category": "Plates",
    "design": 3023,
    "element_name": "PLATE 1X2",
    "element_in_sets": 690,
    "element_introduced_in": 1992,
    "design_in_sets": 15413,
    "design_introduced_in": 1981
  },
  {
    "element_id": 4210997,
    "colour": "Dark Stone Grey",
    "category": "Plates",
    "design": 3034,
    "element_name": "PLATE 2X8",
    "element_in_sets": 548,
    "element_introduced_in": 2002,
    "design_in_sets": 4109,
    "design_introduced_in": 1980
  },
  {
    "element_id": 4211001,
    "colour": "Dark Stone Grey",
    "category": "Plates",
    "design": 3710,
    "element_name": "PLATE 1X4",
    "element_in_sets": 932,
    "element_introduced_in": 1991,
    "design_in_sets": 10753,
    "design_introduced_in": 1981
  },
  {
    "element_id": 4211043,
    "colour": "Dark Stone Grey",
    "category": "Plates",
    "design": 3021,
    "element_name": "PLATE 2X3",
    "element_in_sets": 885,
    "element_introduced_in": 2002,
    "design_in_sets": 7912,
    "design_introduced_in": 1980
  },
  {
    "element_id": 4212529,
    "colour": "Dark Stone Grey",
    "category": "Vehicles & Transportation",
    "design": 30395,
    "element_name": "HOOK W. BALL 1X3",
    "element_in_sets": 179,
    "element_introduced_in": 1999,
    "design_in_sets": 186,
    "design_introduced_in": 1999
  },
  {
    "element_id": 4620079,
    "colour": "Dark Stone Grey",
    "category": "Plates",
    "design": 4150,
    "element_name": "FLAT TILE 2X2, ROUND",
    "element_in_sets": 13,
    "element_introduced_in": 2011,
    "design_in_sets": 338,
    "design_introduced_in": 1993
  },
  {
    "element_id": 4523398,
    "colour": "Dark Stone Grey",
    "category": "Technic Beams",
    "design": 57515,
    "element_name": "FORM 5M W. BALL CUUP",
    "element_in_sets": 9,
    "element_introduced_in": 2008,
    "design_in_sets": 18,
    "design_introduced_in": 2008
  },
  {
    "element_id": 4616698,
    "colour": "Medium Blue",
    "category": "Vehicles & Transportation",
    "design": 60212,
    "element_name": "MUDGUARD 2X4 w. hole Ø4.9",
    "element_in_sets": 7,
    "element_introduced_in": 2011,
    "design_in_sets": 260,
    "design_introduced_in": 1994
  },
  {
    "element_id": 4211397,
    "colour": "Medium Stone Grey",
    "category": "Plates",
    "design": 3022,
    "element_name": "PLATE 2X2",
    "element_in_sets": 1042,
    "element_introduced_in": 1991,
    "design_in_sets": 10506,
    "design_introduced_in": 1986
  },
  {
    "element_id": 4211504,
    "colour": "Medium Stone Grey",
    "category": "Vehicles & Transportation",
    "design": 4600,
    "element_name": "BEARING ELEMENT 2X2, DOUBLE",
    "element_in_sets": 140,
    "element_introduced_in": 2004,
    "design_in_sets": 414,
    "design_introduced_in": 1993
  },
  {
    "element_id": 4211151,
    "colour": "Reddish Brown",
    "category": "Plates",
    "design": 3069,
    "element_name": "FLAT TILE 1X2",
    "element_in_sets": 357,
    "element_introduced_in": 2004,
    "design_in_sets": 8471,
    "design_introduced_in": 1991
  },
  {
    "element_id": 4211152,
    "colour": "Reddish Brown",
    "category": "Plates",
    "design": 3623,
    "element_name": "PLATE 1X3",
    "element_in_sets": 329,
    "element_introduced_in": 2004,
    "design_in_sets": 5729,
    "design_introduced_in": 1981
  },
  {
    "element_id": 4221590,
    "colour": "Reddish Brown",
    "category": "Plates",
    "design": 3666,
    "element_name": "PLATE 1X6",
    "element_in_sets": 342,
    "element_introduced_in": 2003,
    "design_in_sets": 6778,
    "design_introduced_in": 1991
  },
  {
    "element_id": 4221744,
    "colour": "Reddish Brown",
    "category": "Plates",
    "design": 3024,
    "element_name": "PLATE 1X1",
    "element_in_sets": 346,
    "element_introduced_in": 2004,
    "design_in_sets": 7002,
    "design_introduced_in": 1986
  },
  {
    "element_id": 4613134,
    "colour": "Reddish Brown",
    "category": "Vehicles & Transportation",
    "design": 93590,
    "element_name": "WHEEL ARCH 2X4 W HORI.NOBS",
    "element_in_sets": 7,
    "element_introduced_in": 2011,
    "design_in_sets": 44,
    "design_introduced_in": 2011
  },
  {
    "element_id": 4616702,
    "colour": "Reddish Brown",
    "category": "Buildings & Furniture",
    "design": 4865,
    "element_name": "WALL ELEMENT 1X2X1",
    "element_in_sets": 9,
    "element_introduced_in": 2011,
    "design_in_sets": 844,
    "design_introduced_in": 1992
  },
  {
    "element_id": 4617030,
    "colour": "Reddish Brown",
    "category": "Plates",
    "design": 2540,
    "element_name": "PLATE 1X2 W. STICK",
    "element_in_sets": 6,
    "element_introduced_in": 2011,
    "design_in_sets": 2357,
    "design_introduced_in": 1992
  },
  {
    "element_id": 4620075,
    "colour": "Reddish Brown",
    "category": "Bricks",
    "design": 6541,
    "element_name": "TECHNIC BRICK 1X1",
    "element_in_sets": 94,
    "element_introduced_in": 2011,
    "design_in_sets": 1743,
    "design_introduced_in": 1994
  },
  {
    "element_id": 4620534,
    "colour": "Reddish Brown",
    "category": "Vehicles & Transportation",
    "design": 4624,
    "element_name": "RIM NARROW W. HOLE Ø8",
    "element_in_sets": 7,
    "element_introduced_in": 2011,
    "design_in_sets": 183,
    "design_introduced_in": 1995
  },
  {
    "element_id": 6011385,
    "colour": "Reddish Brown",
    "category": "Vehicles & Transportation",
    "design": 74967,
    "element_name": "RIM WIDE W.HOLE Ø8.1 X 9",
    "element_in_sets": 7,
    "element_introduced_in": 2011,
    "design_in_sets": 148,
    "design_introduced_in": 2009
  },
  {
    "element_id": 3005740,
    "colour": "Transparent",
    "category": "Plates",
    "design": 30057,
    "element_name": "ROUND PLATE 1X1 - TR.",
    "element_in_sets": 454,
    "element_introduced_in": 1994,
    "design_in_sets": 3332,
    "design_introduced_in": 1992
  },
  {
    "element_id": 4222960,
    "colour": "Transparent Bright Orange",
    "category": "Plates",
    "design": 30057,
    "element_name": "ROUND PLATE 1X1 - TR.",
    "element_in_sets": 279,
    "element_introduced_in": 2004,
    "design_in_sets": 3332,
    "design_introduced_in": 1992
  },
  {
    "element_id": 6393322,
    "colour": "",
    "category": "Bricks",
    "design": 44865,
    "element_name": "BRICK 1X2 W. HORIZONTAL SNAP",
    "element_in_sets": 42,
    "element_introduced_in": 2019,
    "design_in_sets": 216,
    "design_introduced_in": 2010
  },
  {
    "element_id": 235726,
    "colour": "Black",
    "category": "Bricks",
    "design": 2357,
    "element_name": "BRICK CORNER 1X2X2",
    "element_in_sets": 304,
    "element_introduced_in": 1994,
    "design_in_sets": 2316,
    "design_introduced_in": 1993
  },
  {
    "element_id": 242026,
    "colour": "Black",
    "category": "Plates",
    "design": 2420,
    "element_name": "CORNER PLATE 1X2X2",
    "element_in_sets": 726,
    "element_introduced_in": 1991,
    "design_in_sets": 4375,
    "design_introduced_in": 1991
  },
  {
    "element_id": 244526,
    "colour": "Black",
    "category": "Plates",
    "design": 2445,
    "element_name": "PLATE 2X12",
    "element_in_sets": 397,
    "element_introduced_in": 1995,
    "design_in_sets": 1567,
    "design_introduced_in": 1994
  },
  {
    "element_id": 246526,
    "colour": "Black",
    "category": "Bricks",
    "design": 2465,
    "element_name": "BRICK 1X16",
    "element_in_sets": 126,
    "element_introduced_in": 1994,
    "design_in_sets": 593,
    "design_introduced_in": 1993
  },
  {
    "element_id": 300526,
    "colour": "Black",
    "category": "Bricks",
    "design": 3005,
    "element_name": "BRICK 1X1",
    "element_in_sets": 693,
    "element_introduced_in": 1994,
    "design_in_sets": 6882,
    "design_introduced_in": 1991
  },
  {
    "element_id": 300826,
    "colour": "Black",
    "category": "Bricks",
    "design": 3008,
    "element_name": "BRICK 1X8",
    "element_in_sets": 266,
    "element_introduced_in": 1994,
    "design_in_sets": 2075,
    "design_introduced_in": 1992
  },
  {
    "element_id": 301026,
    "colour": "Black",
    "category": "Bricks",
    "design": 3010,
    "element_name": "BRICK 1X4",
    "element_in_sets": 736,
    "element_introduced_in": 1991,
    "design_in_sets": 6572,
    "design_introduced_in": 1991
  },
  {
    "element_id": 302026,
    "colour": "Black",
    "category": "Plates",
    "design": 3020,
    "element_name": "PLATE 2X4",
    "element_in_sets": 1537,
    "element_introduced_in": 1991,
    "design_in_sets": 11421,
    "design_introduced_in": 1980
  },
  {
    "element_id": 416226,
    "colour": "Black",
    "category": "Plates",
    "design": 4162,
    "element_name": "FLAT TILE 1X8",
    "element_in_sets": 456,
    "element_introduced_in": 1993,
    "design_in_sets": 2426,
    "design_introduced_in": 1991
  },
  {
    "element_id": 428226,
    "colour": "Black",
    "category": "Plates",
    "design": 4282,
    "element_name": "PLATE 2X16",
    "element_in_sets": 249,
    "element_introduced_in": 1994,
    "design_in_sets": 1026,
    "design_introduced_in": 1994
  },
  {
    "element_id": 4558170,
    "colour": "Black",
    "category": "Plates",
    "design": 63864,
    "element_name": "FLAT TILE 1x3",
    "element_in_sets": 368,
    "element_introduced_in": 2010,
    "design_in_sets": 2627,
    "design_introduced_in": 2007
  },
  {
    "element_id": 6174917,
    "colour": "Black",
    "category": "Plates",
    "design": 11212,
    "element_name": "PLATE 3X3",
    "element_in_sets": 150,
    "element_introduced_in": 2017,
    "design_in_sets": 812,
    "design_introduced_in": 2012
  },
  {
    "element_id": 6284070,
    "colour": "Black",
    "category": "Plates",
    "design": 35381,
    "element_name": "FLAT TILE 1X1, ROUND",
    "element_in_sets": 260,
    "element_introduced_in": 2016,
    "design_in_sets": 2022,
    "design_introduced_in": 2014
  },
  {
    "element_id": 6302092,
    "colour": "Black",
    "category": "Bricks",
    "design": 65803,
    "element_name": "BRICK 4/3, 16X16 W/ 4.85 HOLE",
    "element_in_sets": 14,
    "element_introduced_in": 2020,
    "design_in_sets": 18,
    "design_introduced_in": 2020
  },
  {
    "element_id": 6302093,
    "colour": "Black",
    "category": "Miscellaneous",
    "design": 55819,
    "element_name": "ELEMENT SEPARATOR, NO. 2",
    "element_in_sets": 11,
    "element_introduced_in": 2020,
    "design_in_sets": 11,
    "design_introduced_in": 2020
  },
  {
    "element_id": 6316462,
    "colour": "Black",
    "category": "Plates",
    "design": 69533,
    "element_name": "FLAT TILE 2X4, NO. 220",
    "element_in_sets": 1,
    "element_introduced_in": 2020,
    "design_in_sets": 1,
    "design_introduced_in": 2020
  },
  {
    "element_id": 6302094,
    "colour": "Black",
    "category": "Technic Beams",
    "design": 67139,
    "element_name": "PANEL 3X5, W/ 4.85 HOLE",
    "element_in_sets": 24,
    "element_introduced_in": 2020,
    "design_in_sets": 24,
    "design_introduced_in": 2020
  },
  {
    "element_id": 6322821,
    "colour": "Bright Purple",
    "category": "Plates",
    "design": 35381,
    "element_name": "FLAT TILE 1X1, ROUND",
    "element_in_sets": 22,
    "element_introduced_in": 2020,
    "design_in_sets": 2022,
    "design_introduced_in": 2014
  },
  {
    "element_id": 242021,
    "colour": "Bright Red",
    "category": "Plates",
    "design": 2420,
    "element_name": "CORNER PLATE 1X2X2",
    "element_in_sets": 321,
    "element_introduced_in": 1994,
    "design_in_sets": 4375,
    "design_introduced_in": 1991
  },
  {
    "element_id": 6322816,
    "colour": "Bright Reddish Violet",
    "category": "Plates",
    "design": 35381,
    "element_name": "FLAT TILE 1X1, ROUND",
    "element_in_sets": 18,
    "element_introduced_in": 2020,
    "design_in_sets": 2022,
    "design_introduced_in": 2014
  },
  {
    "element_id": 6284577,
    "colour": "Bright Yellow",
    "category": "Plates",
    "design": 35381,
    "element_name": "FLAT TILE 1X1, ROUND",
    "element_in_sets": 104,
    "element_introduced_in": 2017,
    "design_in_sets": 2022,
    "design_introduced_in": 2014
  },
  {
    "element_id": 6284596,
    "colour": "Dark Stone Grey",
    "category": "Plates",
    "design": 35381,
    "element_name": "FLAT TILE 1X1, ROUND",
    "element_in_sets": 120,
    "element_introduced_in": 2018,
    "design_in_sets": 2022,
    "design_introduced_in": 2014
  },
  {
    "element_id": 6284587,
    "colour": "Light Purple",
    "category": "Plates",
    "design": 35381,
    "element_name": "FLAT TILE 1X1, ROUND",
    "element_in_sets": 72,
    "element_introduced_in": 2015,
    "design_in_sets": 2022,
    "design_introduced_in": 2014
  },
  {
    "element_id": 6322819,
    "colour": "Medium Azur",
    "category": "Plates",
    "design": 35381,
    "element_name": "FLAT TILE 1X1, ROUND",
    "element_in_sets": 31,
    "element_introduced_in": 2020,
    "design_in_sets": 2022,
    "design_introduced_in": 2014
  },
  {
    "element_id": 302201,
    "colour": "White",
    "category": "Plates",
    "design": 3022,
    "element_name": "PLATE 2X2",
    "element_in_sets": 1125,
    "element_introduced_in": 1986,
    "design_in_sets": 10506,
    "design_introduced_in": 1986
  }
]